bravado/__init__.py
bravado/_equality_util.py
bravado/client.py
bravado/config.py
bravado/docstring_property.py
bravado/exception.py
bravado/fido_client.py
bravado/http_client.py
bravado/http_future.py
bravado/py.typed
bravado/requests_client.py
bravado/response.py
bravado/swagger_model.py
bravado/warning.py
bravado/testing/__init__.py
bravado/testing/integration_test.py
bravado/testing/response_mocks.py
bravado-11.1.0.dist-info/LICENSE.txt
bravado-11.1.0.dist-info/METADATA
bravado-11.1.0.dist-info/WHEEL
bravado-11.1.0.dist-info/top_level.txt
bravado-11.1.0.dist-info/RECORD
