Metadata-Version: 2.1
Name: bravado
Version: 11.1.0
Summary: Library for accessing Swagger-enabled API's
Home-page: https://github.com/Yelp/bravado
Author: Digium, Inc. and Yelp, Inc.
Author-email: opensource+bravado@yelp.com
License: BSD 3-Clause License
Platform: UNKNOWN
Classifier: Development Status :: 5 - Production/Stable
Classifier: Intended Audience :: Developers
Classifier: Topic :: Software Development :: Libraries :: Python Modules
Classifier: License :: OSI Approved :: BSD License
Classifier: Operating System :: OS Independent
Classifier: Programming Language :: Python :: 2.7
Classifier: Programming Language :: Python :: 3.6
Classifier: Programming Language :: Python :: 3.7
Requires-Python: !=3.0,!=3.1,!=3.2,!=3.3,!=3.4,!=3.5.0
Provides-Extra: fido
Provides-Extra: integration-tests
License-File: LICENSE.txt
